asphalt/memcached/__init__.py
asphalt/memcached/component.py
asphalt_memcached-1.0.0.dist-info/DESCRIPTION.rst
asphalt_memcached-1.0.0.dist-info/METADATA
asphalt_memcached-1.0.0.dist-info/RECORD
asphalt_memcached-1.0.0.dist-info/WHEEL
asphalt_memcached-1.0.0.dist-info/entry_points.txt
asphalt_memcached-1.0.0.dist-info/metadata.json
asphalt_memcached-1.0.0.dist-info/top_level.txt
