Metadata-Version: 2.0
Name: asphalt-memcached
Version: 1.0.0
Summary: Memcached integration component for the Asphalt framework
Home-page: https://github.com/asphalt-framework/asphalt-memcached
Author: Alex Grönholm
Author-email: alex.gronholm@nextday.fi
License: Apache License 2.0
Platform: UNKNOWN
Classifier: Development Status :: 5 - Production/Stable
Classifier: Intended Audience :: Developers
Classifier: License :: OSI Approved :: Apache Software License
Classifier: Programming Language :: Python
Classifier: Programming Language :: Python :: 3
Classifier: Programming Language :: Python :: 3.5
Requires-Dist: aiomcache (>=0.3.0)
Requires-Dist: asphalt (~=2.0)
